shelli/__init__.py
shelli/authenticate.py
shelli/cli_parser.py
shelli/conf.py
shelli/execute.py
shelli/host.py
shelli/hostgroup.py
shelli/main.py
shelli/target.py
shelli/transport.py
Shelli-0.3.dist-info/LICENSE
Shelli-0.3.dist-info/METADATA
Shelli-0.3.dist-info/WHEEL
Shelli-0.3.dist-info/entry_points.txt
Shelli-0.3.dist-info/top_level.txt
Shelli-0.3.dist-info/RECORD
