Metadata-Version: 2.1
Name: Shelli
Version: 0.3
Summary: # Shelli
Requires-Dist: fabric (>=2.4.0)
Requires-Dist: cryptography (==2.3)
Requires-Dist: PyYAML (>=5.1)
